bbcli/__init__.py
bbcli/core.py
bbcli-1.0.0.dist-info/licenses/LICENSE
bbcli-1.0.0.dist-info/METADATA
bbcli-1.0.0.dist-info/WHEEL
bbcli-1.0.0.dist-info/entry_points.txt
bbcli-1.0.0.dist-info/top_level.txt
bbcli-1.0.0.dist-info/RECORD
