Metadata-Version: 2.4
Name: bbcli
Version: 1.0.0
Summary: DEPRECATED - Python version no longer maintained. Install the Rust version: cargo install bbc-news-cli
Home-page: https://github.com/hako/bbcli
Author: Calvin Hill
Author-email: Wesley Hill <wesley@hakobaito.co.uk>
License: MIT
Project-URL: Homepage, https://github.com/hako/bbcli
Keywords: bbc,news,console,terminal,deprecated
Classifier: Development Status :: 7 - Inactive
Classifier: Environment :: Console
Classifier: License :: OSI Approved :: MIT License
Classifier: Natural Language :: English
Classifier: Operating System :: Unix
Classifier: Programming Language :: Python :: 2
Classifier: Programming Language :: Python :: 3
Classifier: Topic :: Terminals
Requires-Python: >=2.7
License-File: LICENSE
Dynamic: home-page
Dynamic: license-file
